[
  {
    "artist": "Babe The Blue Ox",
    "image": "https://ui-avatars.com/api/?name=Babe%20The%20Blue%20Ox&size=800&background=1f2937&color=ffffff&bold=true",
    "links": [
      {
        "title": "Babe The Blue Ox Live at Lounge Ax 1993-04-10",
        "url": "https://archive.org/details/ajc02126_babe-the-blue-ox-1993-04-10"
      },
      {
        "title": "Babe The Blue Ox Live at Lounge Ax 1993-07-02",
        "url": "https://archive.org/details/ajc02127_babe-the-blue-ox-1993-07-02"
      }
    ]
  },
  {
    "artist": "Babes in Toyland",
    "image": "https://ui-avatars.com/api/?name=Babes%20in%20Toyland&size=800&background=1f2937&color=ffffff&bold=true",
    "links": [
      {
        "title": "Babes in Toyland Live at Dreamerz 1988-09-08",
        "url": "https://archive.org/details/ajc02129_babes-in-toyland-1988-09-09"
      },
      {
        "title": "Babes In Toyland Live at Empty Bottle 1994-04-28",
        "url": "https://archive.org/details/ajc02130_babes-in-toyland-1994-04-28"
      }
    ]
  },
  {
    "artist": "Baboon",
    "image": "https://ui-avatars.com/api/?name=Baboon&size=800&background=1f2937&color=ffffff&bold=true",
    "links": [
      {
        "title": "Baboon Live at Fireside Bowl 1996-06-11",
        "url": "https://archive.org/details/ajc02128_baboon_1996-06-11"
      }
    ]
  },
  {
    "artist": "Baby Flamehead",
    "image": "https://ui-avatars.com/api/?name=Baby%20Flamehead&size=800&background=1f2937&color=ffffff&bold=true",
    "links": [
      {
        "title": "Baby Flamehead Live at Lounge Ax 1990-10-12",
        "url": "https://archive.org/details/ajc02135_babyflamehead1990-10-12"
      },
      {
        "title": "Baby Flamehead Live at Lounge Ax 1990-12-05",
        "url": "https://archive.org/details/ajc02132_baby-flamehead-1990-12-05"
      },
      {
        "title": "Baby Flamehead Live at Lounge Ax 1992-02-15",
        "url": "https://archive.org/details/ajc02133_baby-flamehead-1992-02-15"
      }
    ]
  },
  {
    "artist": "Baby M",
    "image": "https://ui-avatars.com/api/?name=Baby%20M&size=800&background=1f2937&color=ffffff&bold=true",
    "links": [
      {
        "title": "Baby M Live at Lounge Ax 1993-07-23",
        "url": "https://archive.org/details/ajc02136_baby-m-1993-07-23"
      }
    ]
  },
  {
    "artist": "Baby Magic",
    "image": "https://ui-avatars.com/api/?name=Baby%20Magic&size=800&background=1f2937&color=ffffff&bold=true",
    "links": [
      {
        "title": "Baby Magic Live at The Burlington on 2013-02-09",
        "url": "https://archive.org/details/ajc03029_babymagic_2013-02-09"
      }
    ]
  },
  {
    "artist": "Bad Livers",
    "image": "https://ui-avatars.com/api/?name=Bad%20Livers&size=800&background=1f2937&color=ffffff&bold=true",
    "links": [
      {
        "title": "Bad Livers Live at Lounge Ax on 1991-02-23",
        "url": "https://archive.org/details/ajc02140_badlivers1991-02-23"
      },
      {
        "title": "Bad Livers Live at Lounge Ax on 1991-07-27",
        "url": "https://archive.org/details/ajc02137_badlivers1991-07-27.ajcproject"
      },
      {
        "title": "Bad Livers Live at Lounge Ax on 1992-09-12",
        "url": "https://archive.org/details/ajc02141_badlivers1992-09-12"
      }
    ]
  },
  {
    "artist": "Bailter Space",
    "image": "https://ui-avatars.com/api/?name=Bailter%20Space&size=800&background=1f2937&color=ffffff&bold=true",
    "links": [
      {
        "title": "Bailter Space Live at Lounge Ax 1994-04-23",
        "url": "https://archive.org/details/ajc03019_bailter_space_1994-04-23"
      },
      {
        "title": "Bailter Space Live at Empty Bottle 1995-07-14",
        "url": "https://archive.org/details/ajc02142_bailter_space_1995-07-14"
      }
    ]
  },
  {
    "artist": "Bakamono",
    "image": "https://ui-avatars.com/api/?name=Bakamono&size=800&background=1f2937&color=ffffff&bold=true",
    "links": [
      {
        "title": "Bakamono Live at Satyricon 1995-05-26",
        "url": "https://archive.org/details/ajc02143_bakamono1995-05-26"
      },
      {
        "title": "Bakamono Live at Fireside Bowl 1995-08-03",
        "url": "https://archive.org/details/ajc02144_bakamono1995-08-03"
      }
    ]
  },
  {
    "artist": "Ball Harvester",
    "image": "https://ui-avatars.com/api/?name=Ball%20Harvester&size=800&background=1f2937&color=ffffff&bold=true",
    "links": [
      {
        "title": "Ball Harvester Live at Lounge Ax 1994-04-02",
        "url": "https://archive.org/details/ajc02149_ballharvester1994-04-02"
      },
      {
        "title": "Ball Harvester Live at Lounge Ax 1994-07-07",
        "url": "https://archive.org/details/ajc02150_ballharvester1994-07-07"
      }
    ]
  },
  {
    "artist": "Band of Horses",
    "image": "https://ui-avatars.com/api/?name=Band%20of%20Horses&size=800&background=1f2937&color=ffffff&bold=true",
    "links": [
      {
        "title": "Band of Horses Live at Schubas Tavern 2006-06-07",
        "url": "https://archive.org/details/ajc02866_band-of-horses-2006-06-07"
      }
    ]
  },
  {
    "artist": "Bar-B-Q Killers",
    "image": "https://ui-avatars.com/api/?name=Bar-B-Q%20Killers&size=800&background=1f2937&color=ffffff&bold=true",
    "links": [
      {
        "title": "Bar-B-Q Killers Live at Cabaret Metro 1987-08-23",
        "url": "https://archive.org/details/ajc02175_bar-b-qkillers1987-08-23"
      }
    ]
  },
  {
    "artist": "Barbara Manning",
    "image": "https://ui-avatars.com/api/?name=Barbara%20Manning&size=800&background=1f2937&color=ffffff&bold=true",
    "links": [
      {
        "title": "Barbara Manning Live at Empty Bottle on 1997-07-11",
        "url": "https://archive.org/details/ajc02422_bmanning1997-07-11.ajcproject"
      },
      {
        "title": "Barbara Manning Live at Reckless Records on 1997-07-12",
        "url": "https://archive.org/details/ajc02423_bmanning1997-07-12.ajcproject"
      },
      {
        "title": "Barbara Manning Live at Empty Bottle on 1998-10-17",
        "url": "https://archive.org/details/ajc02421_bmanning1998-10-17.ajcproject"
      }
    ]
  },
  {
    "artist": "Barnes Chernobyl",
    "image": "https://ui-avatars.com/api/?name=Barnes%20Chernobyl&size=800&background=1f2937&color=ffffff&bold=true",
    "links": [
      {
        "title": "Barnes Chernobyl Live at Caliwaukee 2018-03-31",
        "url": "https://archive.org/details/ajc02031_barnes_chernobyl_2018-03-31"
      }
    ]
  },
  {
    "artist": "Barry McCormack",
    "image": "https://ui-avatars.com/api/?name=Barry%20McCormack&size=800&background=1f2937&color=ffffff&bold=true",
    "links": [
      {
        "title": "Barry McCormack Live at Schubas Tavern 2009-04-18",
        "url": "https://archive.org/details/ajc01723_barry-mc-cormack-2009-04-18"
      }
    ]
  },
  {
    "artist": "Bastro",
    "image": "https://ui-avatars.com/api/?name=Bastro&size=800&background=1f2937&color=ffffff&bold=true",
    "links": [
      {
        "title": "Bastro Live at Cubby Bear 1988-07-03",
        "url": "https://archive.org/details/ajc02170_bastro1988-07-03"
      },
      {
        "title": "Bastro Live at Cubby Bear 1990-08-02",
        "url": "https://archive.org/details/ajc02292_bastro-1990-08-02"
      },
      {
        "title": "Bastro Live at Czar Bar 1991-01-13",
        "url": "https://archive.org/details/ajc02293_bastro-1991-01-13"
      },
      {
        "title": "Bastro Live at Lounge Ax 1991-09-11",
        "url": "https://archive.org/details/ajc02290_bastro-1991-09-11"
      },
      {
        "title": "Bastro Live at Lounge Ax 1991-09-21",
        "url": "https://archive.org/details/ajc02294_bastro1991-09-21"
      }
    ]
  },
  {
    "artist": "Baxter",
    "image": "https://ui-avatars.com/api/?name=Baxter&size=800&background=1f2937&color=ffffff&bold=true",
    "links": [
      {
        "title": "Baxter Live at Fireside Bowl 1997-09-06",
        "url": "https://archive.org/details/ajc00085_baxter-1997-09-06"
      }
    ]
  },
  {
    "artist": "Bear Claw",
    "image": "https://ui-avatars.com/api/?name=Bear%20Claw&size=800&background=1f2937&color=ffffff&bold=true",
    "links": [
      {
        "title": "Bear Claw Live at Lincoln Hall 2012-09-29",
        "url": "https://archive.org/details/ajc02855_bearclaw2012-09-29"
      }
    ]
  },
  {
    "artist": "Beastii",
    "image": "https://ui-avatars.com/api/?name=Beastii&size=800&background=1f2937&color=ffffff&bold=true",
    "links": [
      {
        "title": "Beastii Live at Township 2017-06-02",
        "url": "https://archive.org/details/ajc01984_beastii-2017-06-02"
      }
    ]
  },
  {
    "artist": "Beat Happening",
    "image": "https://ui-avatars.com/api/?name=Beat%20Happening&size=800&background=1f2937&color=ffffff&bold=true",
    "links": [
      {
        "title": "Beat Happening Live at Czar Bar 1991-02-28",
        "url": "https://archive.org/details/ajc02075_beathappening1991-02-28"
      }
    ]
  },
  {
    "artist": "Beau Dashus and the Booty Machine",
    "image": "https://ui-avatars.com/api/?name=Beau%20Dashus%20and%20the%20Booty%20Machine&size=800&background=1f2937&color=ffffff&bold=true",
    "links": [
      {
        "title": "Beau Dashus and the Booty Machine Live at Lounge Ax 1990-10-25",
        "url": "https://archive.org/details/ajc02181_beau-dashus-1990-10-25"
      }
    ]
  },
  {
    "artist": "Beau Kinstler",
    "image": "https://ui-avatars.com/api/?name=Beau%20Kinstler&size=800&background=1f2937&color=ffffff&bold=true",
    "links": [
      {
        "title": "Beau Kinstler Live at Schubas Tavern 2006-07-07",
        "url": "https://archive.org/details/ajc02388_beau_kinstler_2006-07-07"
      }
    ]
  },
  {
    "artist": "Bedhead",
    "image": "https://ui-avatars.com/api/?name=Bedhead&size=800&background=1f2937&color=ffffff&bold=true",
    "links": [
      {
        "title": "Bedhead Live at Lounge Ax 1994-05-20",
        "url": "https://archive.org/details/ajc02182_bedhead-1994-05-20"
      }
    ]
  },
  {
    "artist": "Bellatrix",
    "image": "https://ui-avatars.com/api/?name=Bellatrix&size=800&background=1f2937&color=ffffff&bold=true",
    "links": [
      {
        "title": "Bellatrix Live at Empty Bottle 1995-12-29",
        "url": "https://archive.org/details/ajc02186_bellatrix-1995-12-29"
      }
    ]
  },
  {
    "artist": "Belle & Sebastian",
    "image": "https://ui-avatars.com/api/?name=Belle%20%26%20Sebastian&size=800&background=1f2937&color=ffffff&bold=true",
    "links": [
      {
        "title": "Belle & Sebastian Live at Riviera Theatre on 2015-04-03",
        "url": "https://archive.org/details/ajc01810_belleseb2015-04-03.ajcproject"
      },
      {
        "title": "Belle & Sebastian Live at Overture Center for the Arts on 2015-04-04",
        "url": "https://archive.org/details/0151_bs2015-04-04.ajcproject"
      }
    ]
  },
  {
    "artist": "Belly",
    "image": "https://ui-avatars.com/api/?name=Belly&size=800&background=1f2937&color=ffffff&bold=true",
    "links": [
      {
        "title": "Belly Live at Varsity Theatre - Marquette University 1993-10-14",
        "url": "https://archive.org/details/ajc02187_belly-1993-10-14"
      }
    ]
  },
  {
    "artist": "Ben Folds",
    "image": "https://ui-avatars.com/api/?name=Ben%20Folds&size=800&background=1f2937&color=ffffff&bold=true",
    "links": [
      {
        "title": "Ben Folds Live at Duke Ellington Ballroom - Northern Illinois University 2001-12-03",
        "url": "https://archive.org/details/ajc02621_ben-folds-2001-12-03"
      }
    ]
  },
  {
    "artist": "Ben Folds Five",
    "image": "https://ui-avatars.com/api/?name=Ben%20Folds%20Five&size=800&background=1f2937&color=ffffff&bold=true",
    "links": [
      {
        "title": "Ben Folds Five Live at Metro 1997-04-24",
        "url": "https://archive.org/details/ajc02619_ben-folds-five-1997-04-24"
      },
      {
        "title": "Ben Folds Five Live at Alpine Valley Music Theatre - Second Stage 1997-08-02",
        "url": "https://archive.org/details/ajc02617_ben-folds-five-1997-08-02"
      },
      {
        "title": "Ben Folds Five Live at Riviera Theatre 1998-02-15",
        "url": "https://archive.org/details/ajc02618_ben-folds-five-1998-02-15"
      },
      {
        "title": "Ben Folds Five Live at Park West 1999-05-03",
        "url": "https://archive.org/details/ajc02620_ben-folds-five-1999-05-03"
      }
    ]
  },
  {
    "artist": "Ben Lee",
    "image": "https://ui-avatars.com/api/?name=Ben%20Lee&size=800&background=1f2937&color=ffffff&bold=true",
    "links": [
      {
        "title": "Ben Lee Live at Metro on 2003-07-17",
        "url": "https://archive.org/details/ajc00569_benlee2003-07-17.ajcproject"
      }
    ]
  },
  {
    "artist": "Bender",
    "image": "https://ui-avatars.com/api/?name=Bender&size=800&background=1f2937&color=ffffff&bold=true",
    "links": [
      {
        "title": "Bender Live at Czar Bar 1993-10-08",
        "url": "https://archive.org/details/ajc02188_bender-1993-10-08"
      },
      {
        "title": "Bender Live at Empty Bottle 1994-05-06",
        "url": "https://archive.org/details/ajc02189_bender-1994-05-06"
      }
    ]
  },
  {
    "artist": "Bettie Serveert",
    "image": "https://ui-avatars.com/api/?name=Bettie%20Serveert&size=800&background=1f2937&color=ffffff&bold=true",
    "links": [
      {
        "title": "Bettie Serveert Live at Reckless Records 1993-03-27",
        "url": "https://archive.org/details/ajc02248_bettie1993-03-27"
      },
      {
        "title": "Bettie Serveert Live at Metro 1993-10-29",
        "url": "https://archive.org/details/ajc02247_bettie1993-10-29"
      },
      {
        "title": "Bettie Serveert Live at Metro 1997-05-21",
        "url": "https://archive.org/details/ajc02249_bettie1997-05-21"
      },
      {
        "title": "Bettie Serveert Live at Abbey Pub 2003-04-04",
        "url": "https://archive.org/details/ajc02678_bettieserveert2003-04-04"
      }
    ]
  },
  {
    "artist": "Bev Rage & The Drinks",
    "image": "https://ui-avatars.com/api/?name=Bev%20Rage%20%26%20The%20Drinks&size=800&background=1f2937&color=ffffff&bold=true",
    "links": [
      {
        "title": "Bev Rage & The Drinks Live at Caliwaukee 2018",
        "url": "https://archive.org/details/ajc02032_bev-rage-2018-03-31"
      }
    ]
  },
  {
    "artist": "Bewitched",
    "image": "https://ui-avatars.com/api/?name=Bewitched&size=800&background=1f2937&color=ffffff&bold=true",
    "links": [
      {
        "title": "Bewitched Live at Lounge Ax 1992-05-13",
        "url": "https://archive.org/details/ajc02251_bewitched1992-05-13"
      }
    ]
  },
  {
    "artist": "Bienen School's Contemporary/Early Vocal, Contemporary Music and Saxophone Ensembles",
    "image": "https://ui-avatars.com/api/?name=Bienen%20School%27s%20Contemporary/Early%20Vocal%2C%20Contemporary%20Music%20and%20Saxophone%20Ensembles&size=800&background=1f2937&color=ffffff&bold=true",
    "links": [
      {
        "title": "Bienen School's Contemporary/Early Vocal, Contemporary Music and Saxophone Ensembles Live at Pick-Staiger Concert Hall 2017-11-16",
        "url": "https://archive.org/details/ajc02012_bienen-school-2017-11-16"
      }
    ]
  },
  {
    "artist": "Bienen School's Percussion Ensemble",
    "image": "https://ui-avatars.com/api/?name=Bienen%20School%27s%20Percussion%20Ensemble&size=800&background=1f2937&color=ffffff&bold=true",
    "links": [
      {
        "title": "Bienen School's Percussion Ensemble Live at Pick-Staiger Concert Hall 2017-11-15",
        "url": "https://archive.org/details/ajc02010_bienen-school-2017-11-15"
      }
    ]
  },
  {
    "artist": "Big Chief",
    "image": "https://ui-avatars.com/api/?name=Big%20Chief&size=800&background=1f2937&color=ffffff&bold=true",
    "links": [
      {
        "title": "Big Chief Live at Club Dreamerz 1989-10-28",
        "url": "https://archive.org/details/ajc02250_big-chief-1989-10-28"
      }
    ]
  },
  {
    "artist": "Big Dipper",
    "image": "https://ui-avatars.com/api/?name=Big%20Dipper&size=800&background=1f2937&color=ffffff&bold=true",
    "links": [
      {
        "title": "Big Dipper Live at Cabaret Metro 1987-11-07",
        "url": "https://archive.org/details/ajc02252_big-dipper-1987-11-07"
      },
      {
        "title": "Big Dipper Live at Cubby Bear 1988-02-27",
        "url": "https://archive.org/details/ajc02253_big-dipper-1988-02-27"
      },
      {
        "title": "Big Dipper Live at Cabaret Metro 1989-02-10",
        "url": "https://archive.org/details/ajc02255_big-dipper-1989-02-10"
      },
      {
        "title": "Big Dipper Live at Cabaret Metro 1989-10-07",
        "url": "https://archive.org/details/ajc02254_big-dipper-1989-10-07"
      },
      {
        "title": "Big Dipper Live at Lounge Ax 1990-07-07",
        "url": "https://archive.org/details/ajc02256_big-dipper-1990-07-07"
      }
    ]
  },
  {
    "artist": "Big Fish Ensemble",
    "image": "https://ui-avatars.com/api/?name=Big%20Fish%20Ensemble&size=800&background=1f2937&color=ffffff&bold=true",
    "links": [
      {
        "title": "Big Fish Ensemble Live at Lounge Ax 1992-06-27",
        "url": "https://archive.org/details/ajc02257_bfe_1992-06-27"
      }
    ]
  },
  {
    "artist": "Big Heifer",
    "image": "https://ui-avatars.com/api/?name=Big%20Heifer&size=800&background=1f2937&color=ffffff&bold=true",
    "links": [
      {
        "title": "Big Heifer Live at Lounge Ax 1994-10-22",
        "url": "https://archive.org/details/ajc02275_bigheifer1994-10-22"
      },
      {
        "title": "Big Heifer Live at Lounge Ax 1996-03-23",
        "url": "https://archive.org/details/ajc02276_bigheifer1996-03-23"
      }
    ]
  },
  {
    "artist": "Big Joy",
    "image": "https://ui-avatars.com/api/?name=Big%20Joy&size=800&background=1f2937&color=ffffff&bold=true",
    "links": [
      {
        "title": "Big Joy Live at Schubas Tavern 2015-06-27",
        "url": "https://archive.org/details/0153_big-joy-2015-06-27"
      }
    ]
  },
  {
    "artist": "Big Science",
    "image": "https://ui-avatars.com/api/?name=Big%20Science&size=800&background=1f2937&color=ffffff&bold=true",
    "links": [
      {
        "title": "Big Science Live at Bottom Lounge 2010-03-06",
        "url": "https://archive.org/details/ajc01432_big_science_2010-03-06"
      }
    ]
  },
  {
    "artist": "Big Star",
    "image": "https://ui-avatars.com/api/?name=Big%20Star&size=800&background=1f2937&color=ffffff&bold=true",
    "links": [
      {
        "title": "Big Star Live at Caberet Metro 1999-05-06",
        "url": "https://archive.org/details/ajc00899_big-star-1999-05-06"
      }
    ]
  },
  {
    "artist": "Big Trouble House",
    "image": "https://ui-avatars.com/api/?name=Big%20Trouble%20House&size=800&background=1f2937&color=ffffff&bold=true",
    "links": [
      {
        "title": "Big Trouble House Live at Edge of the Looking Glass 1990-02-23",
        "url": "https://archive.org/details/ajc02278_bth_1990-02-23"
      },
      {
        "title": "Big Trouble House Live at Edge of the Looking Glass 1990-10-27",
        "url": "https://archive.org/details/ajc02279_bth_1990-10-27"
      }
    ]
  },
  {
    "artist": "Big Wheel",
    "image": "https://ui-avatars.com/api/?name=Big%20Wheel&size=800&background=1f2937&color=ffffff&bold=true",
    "links": [
      {
        "title": "Big Wheel Live at Lounge Ax 1990-09-21",
        "url": "https://archive.org/details/ajc02280_bigwheel1990-09-21"
      }
    ]
  },
  {
    "artist": "Big'n",
    "image": "https://ui-avatars.com/api/?name=Big%27n&size=800&background=1f2937&color=ffffff&bold=true",
    "links": [
      {
        "title": "Big'n Live at Empty Bottle 1998-04-20",
        "url": "https://archive.org/details/ajc01472_bign1998-04-20"
      }
    ]
  },
  {
    "artist": "BIGCOLOUR",
    "image": "https://ui-avatars.com/api/?name=BIGCOLOUR&size=800&background=1f2937&color=ffffff&bold=true",
    "links": [
      {
        "title": "BIGCOLOUR Live at Empty Bottle 2011-10-18",
        "url": "https://archive.org/details/ajc02706_bigcolour-2011-10-18"
      }
    ]
  },
  {
    "artist": "Bigger Lovers",
    "image": "https://ui-avatars.com/api/?name=Bigger%20Lovers&size=800&background=1f2937&color=ffffff&bold=true",
    "links": [
      {
        "title": "Bigger Lovers Live at Schubas Tavern 2002-09-18",
        "url": "https://archive.org/details/ajc00936_bigger-lovers-2002-09-18"
      },
      {
        "title": "Bigger Lovers Live at Schubas Tavern 2002-12-10",
        "url": "https://archive.org/details/ajc00937_bigger-lovers-2002-12-10"
      },
      {
        "title": "Bigger Lovers Live at Hideout 2003-03-27",
        "url": "https://archive.org/details/ajc00938_bigger-lovers-2003-03-27"
      }
    ]
  },
  {
    "artist": "Bill Direen",
    "image": "https://ui-avatars.com/api/?name=Bill%20Direen&size=800&background=1f2937&color=ffffff&bold=true",
    "links": [
      {
        "title": "Bill Direen Live at Ajax 1994-08-08",
        "url": "https://archive.org/details/ajc02432_billdireen1994-08-08"
      }
    ]
  },
  {
    "artist": "Billy Bragg",
    "image": "https://ui-avatars.com/api/?name=Billy%20Bragg&size=800&background=1f2937&color=ffffff&bold=true",
    "links": [
      {
        "title": "Billy Bragg Live at Cabaret Metro on 1986-12-04",
        "url": "https://archive.org/details/ajc02362_bbragg1986-12-04.ajcproject"
      },
      {
        "title": "Billy Bragg Live at Cabaret Metro on 1988-05-06",
        "url": "https://archive.org/details/ajc02359_bbragg1988-05-06.ajcproject"
      }
    ]
  },
  {
    "artist": "Bimbo Shrineheads",
    "image": "https://ui-avatars.com/api/?name=Bimbo%20Shrineheads&size=800&background=1f2937&color=ffffff&bold=true",
    "links": [
      {
        "title": "Bimbo Shrineheads Live at Phyllis' Musical Inn 1991-08-28",
        "url": "https://archive.org/details/ajc02284_bimbo-shrineheads-1991-08-28"
      }
    ]
  },
  {
    "artist": "Birdland",
    "image": "https://ui-avatars.com/api/?name=Birdland&size=800&background=1f2937&color=ffffff&bold=true",
    "links": [
      {
        "title": "Birdland Live at Lounge Ax 1991-06-30",
        "url": "https://archive.org/details/ajc02283_birdland-1991-06-30"
      }
    ]
  },
  {
    "artist": "Bitch Magnet",
    "image": "https://ui-avatars.com/api/?name=Bitch%20Magnet&size=800&background=1f2937&color=ffffff&bold=true",
    "links": [
      {
        "title": "Bitch Magnet Live at Reckless Records 1990-10-18",
        "url": "https://archive.org/details/ajc02285_bitch_magnet_1990-10-18"
      }
    ]
  },
  {
    "artist": "Bitchin Bajas",
    "image": "https://ui-avatars.com/api/?name=Bitchin%20Bajas&size=800&background=1f2937&color=ffffff&bold=true",
    "links": [
      {
        "title": "Bitchin Bajas Live at Hideout 2014-04-17",
        "url": "https://archive.org/details/ajc00289_bitchin-bajas-2014-04-17"
      }
    ]
  },
  {
    "artist": "Bite",
    "image": "https://ui-avatars.com/api/?name=Bite&size=800&background=1f2937&color=ffffff&bold=true",
    "links": [
      {
        "title": "Bite Live at Lounge Ax 1994-11-13",
        "url": "https://archive.org/details/ajc02286_bite-1994-11-13"
      }
    ]
  },
  {
    "artist": "Bivouac",
    "image": "https://ui-avatars.com/api/?name=Bivouac&size=800&background=1f2937&color=ffffff&bold=true",
    "links": [
      {
        "title": "Bivouac Live at Town & Country Club 1993-12-06",
        "url": "https://archive.org/details/ajc02287_bivouac_1993-12-06"
      }
    ]
  },
  {
    "artist": "Björk",
    "image": "https://ui-avatars.com/api/?name=Bj%C3%B6rk&size=800&background=1f2937&color=ffffff&bold=true",
    "links": [
      {
        "title": "Björk Live at Pitchfork Music Festival 2013-07-19",
        "url": "https://archive.org/details/0123_bjork2013-07-19"
      }
    ]
  },
  {
    "artist": "Black Mountain",
    "image": "https://ui-avatars.com/api/?name=Black%20Mountain&size=800&background=1f2937&color=ffffff&bold=true",
    "links": [
      {
        "title": "Black Mountain Live at Schubas Tavern on 2005-04-08",
        "url": "https://archive.org/details/ajc00964_BlackMountain2005-04-08.ajcproject"
      }
    ]
  },
  {
    "artist": "Blacktop",
    "image": "https://ui-avatars.com/api/?name=Blacktop&size=800&background=1f2937&color=ffffff&bold=true",
    "links": [
      {
        "title": "Blacktop Live at Empty Bottle 1995-07-01",
        "url": "https://archive.org/details/ajc02161_blacktop-1995-07-01"
      }
    ]
  },
  {
    "artist": "Blake Babies",
    "image": "https://ui-avatars.com/api/?name=Blake%20Babies&size=800&background=1f2937&color=ffffff&bold=true",
    "links": [
      {
        "title": "Blake Babies Live at Double Door 2001-06-09",
        "url": "https://archive.org/details/ajc02330_blake-babies-2001-06-09"
      }
    ]
  },
  {
    "artist": "Blake Zwieg",
    "image": "https://ui-avatars.com/api/?name=Blake%20Zwieg&size=800&background=1f2937&color=ffffff&bold=true",
    "links": [
      {
        "title": "Blake Zwieg Live at Schubas Tavern 2002-05-27",
        "url": "https://archive.org/details/ajc01530_blake-zwieg-2002-05-27"
      }
    ]
  },
  {
    "artist": "Blast Off Country Style",
    "image": "https://ui-avatars.com/api/?name=Blast%20Off%20Country%20Style&size=800&background=1f2937&color=ffffff&bold=true",
    "links": [
      {
        "title": "Blast Off Country Style Live at Double Door 1994-09-30",
        "url": "https://archive.org/details/ajc02159_blast-off-country-style_1994-09-30"
      },
      {
        "title": "Blast Off Country Style Live at Empty Bottle 1996-04-08",
        "url": "https://archive.org/details/ajc02160_blastoffcountrystyle_1996-04-08"
      }
    ]
  },
  {
    "artist": "Bleached Black",
    "image": "https://ui-avatars.com/api/?name=Bleached%20Black&size=800&background=1f2937&color=ffffff&bold=true",
    "links": [
      {
        "title": "Bleached Black Live at Cabaret Metro 1987-09-23",
        "url": "https://archive.org/details/ajc02164_bleached-black-1987-09-23"
      }
    ]
  },
  {
    "artist": "Bleary",
    "image": "https://ui-avatars.com/api/?name=Bleary&size=800&background=1f2937&color=ffffff&bold=true",
    "links": [
      {
        "title": "Bleary Live at Lounge Ax 1997-11-09",
        "url": "https://archive.org/details/ajc02162_bleary-1997-11-09"
      }
    ]
  },
  {
    "artist": "Bleep",
    "image": "https://ui-avatars.com/api/?name=Bleep&size=800&background=1f2937&color=ffffff&bold=true",
    "links": [
      {
        "title": "Bleep Live at Empty Bottle 1997-04-17",
        "url": "https://archive.org/details/ajc02331_bleep_1997-04-17"
      },
      {
        "title": "Bleep Live at Empty Bottle 1997-06-16",
        "url": "https://archive.org/details/ajc02332_bleep_1997-06-16"
      },
      {
        "title": "Bleep Live at Empty Bottle 1997-07-28",
        "url": "https://archive.org/details/ajc02333_bleep_1997-07-28"
      },
      {
        "title": "Bleep Live at Schubas Tavern 2002-05-16",
        "url": "https://archive.org/details/ajc02429_bleep_2002-05-16"
      }
    ]
  },
  {
    "artist": "Bleu",
    "image": "https://ui-avatars.com/api/?name=Bleu&size=800&background=1f2937&color=ffffff&bold=true",
    "links": [
      {
        "title": "Bleu Live at Schubas Tavern 2002-10-17",
        "url": "https://archive.org/details/ajc02326_bleu-2002-10-17"
      }
    ]
  },
  {
    "artist": "Blind Luck Music",
    "image": "https://ui-avatars.com/api/?name=Blind%20Luck%20Music&size=800&background=1f2937&color=ffffff&bold=true",
    "links": [
      {
        "title": "Blind Luck Music Live at Fireside Bowl 2002-07-23",
        "url": "https://archive.org/details/ajc01644_blindluckmusic2002-07-23"
      }
    ]
  },
  {
    "artist": "Blind Moon",
    "image": "https://ui-avatars.com/api/?name=Blind%20Moon&size=800&background=1f2937&color=ffffff&bold=true",
    "links": [
      {
        "title": "Blind Moon Live at Schubas Tavern 2016-04-30",
        "url": "https://archive.org/details/ajc01893_blind-moon-2016-04-30"
      }
    ]
  },
  {
    "artist": "Blindive",
    "image": "https://ui-avatars.com/api/?name=Blindive&size=800&background=1f2937&color=ffffff&bold=true",
    "links": [
      {
        "title": "Blindive Live at Lounge Ax 1996-04-26",
        "url": "https://archive.org/details/ajc01466_blindive-1996-04-26"
      }
    ]
  },
  {
    "artist": "Blithe",
    "image": "https://ui-avatars.com/api/?name=Blithe&size=800&background=1f2937&color=ffffff&bold=true",
    "links": [
      {
        "title": "Blithe Live at Lounge Ax 1996-09-14",
        "url": "https://archive.org/details/ajc02166_blithe-1996-09-14"
      }
    ]
  },
  {
    "artist": "Blonde Redhead",
    "image": "https://ui-avatars.com/api/?name=Blonde%20Redhead&size=800&background=1f2937&color=ffffff&bold=true",
    "links": [
      {
        "title": "Blonde Redhead Live at Empty Bottle 1995-11-21",
        "url": "https://archive.org/details/ajc02308_blonde-redhead-1995-11-21"
      },
      {
        "title": "Blonde Redhead Live at Lounge Ax 1996-05-23",
        "url": "https://archive.org/details/ajc02309_blonde-redhead-1996-05-23"
      }
    ]
  },
  {
    "artist": "Blood Circus",
    "image": "https://ui-avatars.com/api/?name=Blood%20Circus&size=800&background=1f2937&color=ffffff&bold=true",
    "links": [
      {
        "title": "Blood Circus Live at Cubby Bear 1989-06-21",
        "url": "https://archive.org/details/ajc02310_blood-circus-1989-06-21"
      }
    ]
  },
  {
    "artist": "Bloodiest",
    "image": "https://ui-avatars.com/api/?name=Bloodiest&size=800&background=1f2937&color=ffffff&bold=true",
    "links": [
      {
        "title": "Bloodiest Live at Logan Square Park 2011-06-26",
        "url": "https://archive.org/details/ajc02334_bloodiest-2011-06-26"
      }
    ]
  },
  {
    "artist": "Bloody Knuckles Club",
    "image": "https://ui-avatars.com/api/?name=Bloody%20Knuckles%20Club&size=800&background=1f2937&color=ffffff&bold=true",
    "links": [
      {
        "title": "Bloody Knuckles Club Live at Empty Bottle 1994-07-14",
        "url": "https://archive.org/details/ajc02312_bloody-knuckles-club-1994-07-14"
      }
    ]
  },
  {
    "artist": "Blow Torch",
    "image": "https://ui-avatars.com/api/?name=Blow%20Torch&size=800&background=1f2937&color=ffffff&bold=true",
    "links": [
      {
        "title": "Blow Torch Live at Cabaret Metro 1986-12-04",
        "url": "https://archive.org/details/ajc02363_blow-torch-1986-12-04"
      }
    ]
  },
  {
    "artist": "Blue Aeroplanes",
    "image": "https://ui-avatars.com/api/?name=Blue%20Aeroplanes&size=800&background=1f2937&color=ffffff&bold=true",
    "links": [
      {
        "title": "Blue Aeroplanes Live at Lounge Ax 1989-11-04",
        "url": "https://archive.org/details/ajc02314_blueaeroplanes1989-11-04"
      }
    ]
  },
  {
    "artist": "Blue Birds & Bright Lights",
    "image": "https://ui-avatars.com/api/?name=Blue%20Birds%20%26%20Bright%20Lights&size=800&background=1f2937&color=ffffff&bold=true",
    "links": [
      {
        "title": "Blue Birds & Bright Lights Live at Beat Kitchen 2007-08-18",
        "url": "https://archive.org/details/ajc01617_bluebirdsbrightlights2007-08-18"
      }
    ]
  },
  {
    "artist": "Blue Eyed Shags",
    "image": "https://ui-avatars.com/api/?name=Blue%20Eyed%20Shags&size=800&background=1f2937&color=ffffff&bold=true",
    "links": [
      {
        "title": "Blue Eyed Shags Live at Phyllis' Musical Inn 1993-07-10",
        "url": "https://archive.org/details/ajc02585_blue_eyed_shags_1993-07-10"
      }
    ]
  },
  {
    "artist": "Blue Hippos",
    "image": "https://ui-avatars.com/api/?name=Blue%20Hippos&size=800&background=1f2937&color=ffffff&bold=true",
    "links": [
      {
        "title": "Blue Hippos Live at Cabaret Metro 1989-05-05",
        "url": "https://archive.org/details/ajc02315_blue-hippos-1989-05-05"
      }
    ]
  },
  {
    "artist": "Bluetip",
    "image": "https://ui-avatars.com/api/?name=Bluetip&size=800&background=1f2937&color=ffffff&bold=true",
    "links": [
      {
        "title": "Bluetip Live at Metro 2000-09-28",
        "url": "https://archive.org/details/ajc01497_bluetip_2000-09-28"
      }
    ]
  },
  {
    "artist": "Blunderbuss",
    "image": "https://ui-avatars.com/api/?name=Blunderbuss&size=800&background=1f2937&color=ffffff&bold=true",
    "links": [
      {
        "title": "Blunderbuss Live at Lounge Ax 1992-08-05",
        "url": "https://archive.org/details/ajc02320_blunderbuss_1992-08-05"
      }
    ]
  },
  {
    "artist": "BOB",
    "image": "https://ui-avatars.com/api/?name=BOB&size=800&background=1f2937&color=ffffff&bold=true",
    "links": [
      {
        "title": "BOB Live at Rough Trade 1987-12-12",
        "url": "https://archive.org/details/ajc02358_bob_1987-12-12"
      }
    ]
  },
  {
    "artist": "Bob Evans",
    "image": "https://ui-avatars.com/api/?name=Bob%20Evans&size=800&background=1f2937&color=ffffff&bold=true",
    "links": [
      {
        "title": "Bob Evans Live at Lounge Ax 1994-02-03",
        "url": "https://archive.org/details/ajc02321_bob_evans_1994-02-03"
      }
    ]
  },
  {
    "artist": "Bob Rising & Scenario",
    "image": "https://ui-avatars.com/api/?name=Bob%20Rising%20%26%20Scenario&size=800&background=1f2937&color=ffffff&bold=true",
    "links": [
      {
        "title": "Bob Rising & Scenario Live at Metro 1997-01-04",
        "url": "https://archive.org/details/ajc02520_brs_1997-01-04"
      }
    ]
  },
  {
    "artist": "Bobby Bare Jr.",
    "image": "https://ui-avatars.com/api/?name=Bobby%20Bare%20Jr.&size=800&background=1f2937&color=ffffff&bold=true",
    "links": [
      {
        "title": "Bobby Bare Jr. Live at Hideout Block Party 2009-09-12",
        "url": "https://archive.org/details/ajc03119_bobbybarejr2009-09-12"
      }
    ]
  },
  {
    "artist": "Bobby Conn",
    "image": "https://ui-avatars.com/api/?name=Bobby%20Conn&size=800&background=1f2937&color=ffffff&bold=true",
    "links": [
      {
        "title": "Bobby Conn Live at Empty Bottle 2001-09-06",
        "url": "https://archive.org/details/ajc00267_bobbyconn2001-09-06"
      },
      {
        "title": "Bobby Conn Live at Tower Records",
        "url": "https://archive.org/details/ajc01453_bobby-conn_2005-03-05"
      },
      {
        "title": "Bobby Conn Live at Andersonville City Made Fest 2015-09-12",
        "url": "https://archive.org/details/ajc_0207_bobby-conn-2015-09-12"
      }
    ]
  },
  {
    "artist": "Bodeco",
    "image": "https://ui-avatars.com/api/?name=Bodeco&size=800&background=1f2937&color=ffffff&bold=true",
    "links": [
      {
        "title": "Bodeco Live at Lounge Ax 1991-08-01",
        "url": "https://archive.org/details/ajc02323_bodeco_1991-08-01"
      },
      {
        "title": "Bodeco Live at Lounge Ax 1994-07-28",
        "url": "https://archive.org/details/ajc02324_bodeco-live-at-lounge-ax-1994-07-28"
      }
    ]
  },
  {
    "artist": "Bone & Bell",
    "image": "https://ui-avatars.com/api/?name=Bone%20%26%20Bell&size=800&background=1f2937&color=ffffff&bold=true",
    "links": [
      {
        "title": "Bone & Bell Live at Schubas Tavern 2010-10-18",
        "url": "https://archive.org/details/ajc00941_boneandbell2010-10-18"
      },
      {
        "title": "Bone & Bell Live at Quenchers Saloon 2012-03-03",
        "url": "https://archive.org/details/ajc02744_bonebell2012-03-03"
      },
      {
        "title": "Bone & Bell Live at Schubas Tavern 2012-05-25",
        "url": "https://archive.org/details/ajc02801_bonebell2012-05-25"
      }
    ]
  },
  {
    "artist": "Boogarins",
    "image": "https://ui-avatars.com/api/?name=Boogarins&size=800&background=1f2937&color=ffffff&bold=true",
    "links": [
      {
        "title": "Boogarins Live at Lincoln Hall 2014-08-18",
        "url": "https://archive.org/details/ajc01825_boogarins_2014-08-18"
      }
    ]
  },
  {
    "artist": "Boom Hank",
    "image": "https://ui-avatars.com/api/?name=Boom%20Hank&size=800&background=1f2937&color=ffffff&bold=true",
    "links": [
      {
        "title": "Boom Hank Live at Elbo Room 1991-08-03",
        "url": "https://archive.org/details/ajc02341_boom-hank-1991-08-03"
      },
      {
        "title": "Boom Hank Live at Lounge Ax 1994-04-06",
        "url": "https://archive.org/details/ajc02340_boom-hank-1994-04-06"
      },
      {
        "title": "Boom Hank Live at Abbey Pub 2010-01-22",
        "url": "https://archive.org/details/ajc00942_boom_hank_2010-01-22"
      }
    ]
  },
  {
    "artist": "Boredoms",
    "image": "https://ui-avatars.com/api/?name=Boredoms&size=800&background=1f2937&color=ffffff&bold=true",
    "links": [
      {
        "title": "Boredoms Live at Intonation Festival - Union Park 2006-06-24",
        "url": "https://archive.org/details/ajc00957_boredoms_2006-06-24"
      }
    ]
  },
  {
    "artist": "Boris The Sprinkler",
    "image": "https://is1-ssl.mzstatic.com/image/thumb/Music113/v4/96/c8/f1/96c8f12d-72c0-1887-f7b0-a1689c7df5aa/669910900802.jpg/1200x1200bb.jpg",
    "links": [
      {
        "title": "Boris The Sprinkler Live at John J Lewis Room, Morris Center - Northwestern University 1995-07-09",
        "url": "https://archive.org/details/ajc02343_boris-the-sprinkler-1995-07-09"
      }
    ]
  },
  {
    "artist": "Born To Run",
    "image": "https://is1-ssl.mzstatic.com/image/thumb/Music112/v4/18/19/2d/18192d4a-11d1-ce4e-5084-fd1717d67245/artwork.jpg/1200x1200bb.jpg",
    "links": [
      {
        "title": "Born To Run Live at Lounge Ax 1996-03-14",
        "url": "https://archive.org/details/ajc02344_born_to_run_1996-03-14"
      }
    ]
  },
  {
    "artist": "Boy King",
    "image": "https://is1-ssl.mzstatic.com/image/thumb/Music116/v4/0f/19/eb/0f19eb0e-1d72-9b00-6e3b-4a8a6fca817d/18UMGIM52342.rgb.jpg/1200x1200bb.jpg",
    "links": [
      {
        "title": "Boy King Live at Lounge Ax 1993-08-27",
        "url": "https://archive.org/details/ajc02588_boy_king_1993-08-27"
      },
      {
        "title": "Boy King Live at Empty Bottle 1994-02-25",
        "url": "https://archive.org/details/ajc02590_boy_king_1994-02-25"
      },
      {
        "title": "Boy King Live at Lounge Ax 1994-08-15",
        "url": "https://archive.org/details/ajc02591_boy_king_1994-08-15"
      },
      {
        "title": "Boy King Live at Lounge Ax 1994-08-18",
        "url": "https://archive.org/details/ajc02592_boy_king_1994-08-18"
      },
      {
        "title": "Boy King Live at Empty Bottle 1994-12-04",
        "url": "https://archive.org/details/ajc02593_boy_king_1994-12-04"
      }
    ]
  },
  {
    "artist": "Boyracer",
    "image": "https://is1-ssl.mzstatic.com/image/thumb/Music/e7/e2/45/mzi.sfdzoant.jpg/1200x1200bb.jpg",
    "links": [
      {
        "title": "Boyracer Live at Empty Bottle 1994-10-29",
        "url": "https://archive.org/details/ajc02348_boyracer_1994-10-29"
      },
      {
        "title": "Boyracer Live at Empty Bottle 1996-05-25",
        "url": "https://archive.org/details/ajc02349_boyracer_1996-05-25"
      }
    ]
  },
  {
    "artist": "Boys Life",
    "image": "https://is1-ssl.mzstatic.com/image/thumb/Music112/v4/f1/f4/e1/f1f4e1f6-6c0d-6cf7-d6e4-69a7729abfeb/37053.jpg/1200x1200bb.jpg",
    "links": [
      {
        "title": "Boys Life Live at Empty Bottle 1995-01-28",
        "url": "https://archive.org/details/ajc02351_boys-life-1995-01-28"
      },
      {
        "title": "Boys Life Live at Empty Bottle 1995-02-25",
        "url": "https://archive.org/details/ajc02352_boys-life-1995-02-25"
      },
      {
        "title": "Boys Life Live at Fireside Bowl 1995-03-01",
        "url": "https://archive.org/details/ajc02353_boys-life-1995-03-01"
      },
      {
        "title": "Boys Life Live at Fireside Bowl 1995-06-09",
        "url": "https://archive.org/details/ajc02354_boys-life-1995-06-09"
      },
      {
        "title": "Boys Life Live at Empty Bottle 1995-08-18",
        "url": "https://archive.org/details/ajc02355_boys-life-1995-08-18"
      },
      {
        "title": "Boys Life Live at Empty Bottle 1995-08-28",
        "url": "https://archive.org/details/ajc02356_boys-life-1995-08-28"
      }
    ]
  },
  {
    "artist": "Braid",
    "image": "https://is1-ssl.mzstatic.com/image/thumb/Music/y2004/m06/d07/h20/s05.pnopabtx.jpg/1200x1200bb.jpg",
    "links": [
      {
        "title": "Braid Live at Metro 2011-08-27",
        "url": "https://archive.org/details/ajc000967_braid-2011-08-27"
      },
      {
        "title": "Braid Live at Threadless - Pitchfork Pre-Party 2013-07-19",
        "url": "https://archive.org/details/ajc00262_braid-2013-07-19"
      },
      {
        "title": "Braid Live at Empty Bottle 2014-07-20 (Early show)",
        "url": "https://archive.org/details/ajc01824_braid_2014-07-20_early"
      }
    ]
  },
  {
    "artist": "Braille",
    "image": "https://is1-ssl.mzstatic.com/image/thumb/Music124/v4/3f/2e/66/3f2e664f-d2c9-bce3-8a4c-b689b4a18d03/mzi.zjfpsqfp.tif/1200x1200bb.jpg",
    "links": [
      {
        "title": "Braille Live at Fireside Bowl 2003-09-23",
        "url": "https://archive.org/details/ajc01614_braille-2003-09-23"
      }
    ]
  },
  {
    "artist": "Bread And Bottle",
    "image": "https://is1-ssl.mzstatic.com/image/thumb/Music/3e/16/7b/mzi.tecctiyn.jpg/1200x1200bb.jpg",
    "links": [
      {
        "title": "Bread And Bottle Live at Abbey Pub 2009-04-04",
        "url": "https://archive.org/details/ajc01555_bread-and-bottle-2009-04-04"
      }
    ]
  },
  {
    "artist": "Breeders",
    "image": "https://is1-ssl.mzstatic.com/image/thumb/Music126/v4/c7/f2/9c/c7f29c36-434e-3e40-b517-dce503eb2d5c/652637301458.png/1200x1200bb.jpg",
    "links": [
      {
        "title": "Breeders Live at Pitchfork Festival 2013-07-20",
        "url": "https://archive.org/details/0124_breeders2013-07-20"
      }
    ]
  },
  {
    "artist": "Brendan Benson and the Wellfed Boys",
    "image": "https://ui-avatars.com/api/?name=Brendan%20Benson%20and%20the%20Wellfed%20Boys&size=800&background=1f2937&color=ffffff&bold=true",
    "links": [
      {
        "title": "Brendan Benson and the Wellfed Boys Live at Schubas Tavern 2002-08-02",
        "url": "https://archive.org/details/ajc01401_BrendanBenson_2002-08-02"
      }
    ]
  },
  {
    "artist": "Bric-a-Brac",
    "image": "https://is1-ssl.mzstatic.com/image/thumb/Music125/v4/7f/49/41/7f494138-3b15-6653-1b7c-742f15b5616d/859748495162_cover.jpg/1200x1200bb.jpg",
    "links": [
      {
        "title": "Bric-a-Brac Live at Hideout 2001-06-24",
        "url": "https://archive.org/details/ajc00159_bric-a-brac2001-06-24"
      },
      {
        "title": "Bric-a-Brac Live at The Hideout 2007-07-29",
        "url": "https://archive.org/details/ajc00571_bric-a-brac-2007-07-29"
      }
    ]
  },
  {
    "artist": "Brief Candles",
    "image": "https://is1-ssl.mzstatic.com/image/thumb/Music/01/2d/01/mzi.cvgwhhgr.jpg/1200x1200bb.jpg",
    "links": [
      {
        "title": "Brief Candles Live at Resistor 2017-11-03",
        "url": "https://archive.org/details/ajc02005_brief_candles_2017-11-03"
      }
    ]
  },
  {
    "artist": "Bright Eyes",
    "image": "https://is1-ssl.mzstatic.com/image/thumb/Music125/v4/0d/83/fd/0d83fd2e-1cb5-7965-b392-f91f80188290/508.jpg/1200x1200bb.jpg",
    "links": [
      {
        "title": "Bright Eyes Live at Abbey Pub 2003-07-30",
        "url": "https://archive.org/details/ajc00943_bright_eyes_2003-07-30"
      }
    ]
  },
  {
    "artist": "Brock Meyers",
    "image": "https://is1-ssl.mzstatic.com/image/thumb/Music/v4/c7/af/4a/c7af4acd-c13e-063d-d82f-0d2d2dbb257b/884501945264.jpg/1200x1200bb.jpg",
    "links": [
      {
        "title": "Brock Meyers Live at Fireside Bowl 1996-10-10",
        "url": "https://archive.org/details/ajc00042_brock-meyers-1996-10-10"
      }
    ]
  },
  {
    "artist": "Brokeback",
    "image": "https://is1-ssl.mzstatic.com/image/thumb/Music124/v4/70/28/51/702851a0-554a-654c-4add-15d0098c19c1/s05.myocxtim.jpg/1200x1200bb.jpg",
    "links": [
      {
        "title": "Brokeback Live at Hideout 2011-09-30",
        "url": "https://archive.org/details/ajc02700_brokeback2011-09-30"
      },
      {
        "title": "Brokeback Live at Hideout 2012-02-09",
        "url": "https://archive.org/details/ajc02736_brokeback-2012-02-09"
      },
      {
        "title": "Brokeback Live at Hideout 2012-06-12",
        "url": "https://archive.org/details/ajc02807_brokeback-2012-06-12"
      },
      {
        "title": "Brokeback Live at The Hideout 2013-09-28",
        "url": "https://archive.org/details/0210_brokeback_2013-09-28"
      },
      {
        "title": "Brokeback Live at Hideout 2014-05-22",
        "url": "https://archive.org/details/ajc00291_brokeback2014-05-22"
      },
      {
        "title": "Brokeback Live at Schubas Tavern 2015-07-23",
        "url": "https://archive.org/details/0211_brokeback_2015-07-23"
      }
    ]
  },
  {
    "artist": "Brother A. West and His World Salvation Ministry",
    "image": "https://ui-avatars.com/api/?name=Brother%20A.%20West%20and%20His%20World%20Salvation%20Ministry&size=800&background=1f2937&color=ffffff&bold=true",
    "links": [
      {
        "title": "Brother A. West and His World Salvation Ministry Live at Cabaret Metro 1985-11-03",
        "url": "https://archive.org/details/ajc03195_brother-awest-1985-11-03"
      }
    ]
  },
  {
    "artist": "Bryan Scary & The Shredding Tears",
    "image": "https://is1-ssl.mzstatic.com/image/thumb/Music/83/61/d4/mzi.znxplzxl.jpg/1200x1200bb.jpg",
    "links": [
      {
        "title": "Bryan Scary & The Shredding Tears Live at Schubas Tavern 2009-02-26",
        "url": "https://archive.org/details/ajc01276_bryan-scary-2009-02-26"
      }
    ]
  },
  {
    "artist": "Bunnygrunt",
    "image": "https://is1-ssl.mzstatic.com/image/thumb/Music122/v4/bb/2b/dc/bb2bdcd9-799e-f5cd-702f-8d9e5ae57bb0/795103606623.jpg/1200x1200bb.jpg",
    "links": [
      {
        "title": "Bunnygrunt Live at Fireside Bowl on 1995-04-22",
        "url": "https://archive.org/details/ajc03231_bunnygrunt_1995-04-22"
      },
      {
        "title": "Bunnygrunt Live at Fireside Bowl on 1996-10-20",
        "url": "https://archive.org/details/ajc00045_bunnygrunt_1996-10-20"
      },
      {
        "title": "Bunnygrunt Live at Lounge Ax on 1997-06-20",
        "url": "https://archive.org/details/ajc00075_bunnygrunt_1997-06-20"
      }
    ]
  },
  {
    "artist": "Busdriver",
    "image": "https://is1-ssl.mzstatic.com/image/thumb/Music2/v4/cb/45/f2/cb45f232-76cb-108d-5560-abb423f8187d/5021392924298.jpg/1200x1200bb.jpg",
    "links": [
      {
        "title": "Busdriver Live at Empty Bottle 2008-09-12",
        "url": "https://archive.org/details/ajc01681_busdriver-2008-09-12"
      }
    ]
  },
  {
    "artist": "Business Of Dreams",
    "image": "https://is1-ssl.mzstatic.com/image/thumb/Music118/v4/b1/be/8a/b1be8a3e-2e47-2d7c-978b-a26b33dafdce/749846023780.jpg/1200x1200bb.jpg",
    "links": [
      {
        "title": "Business of Dreams Live at Beat Kitchen 2017-04-20",
        "url": "https://archive.org/details/ajc01743_business_of_dreams_2017-04-20"
      }
    ]
  },
  {
    "artist": "By Divine Right",
    "image": "https://is1-ssl.mzstatic.com/image/thumb/Music126/v4/b7/c9/56/b7c956ba-2d12-997d-b338-5a7ca0791f26/196626540300.jpg/1200x1200bb.jpg",
    "links": [
      {
        "title": "By Divine Right Live at Schubas Tavern 2004-09-05",
        "url": "https://archive.org/details/ajc00971_by-divine-right-2004-09-05"
      }
    ]
  }
]